llama_index/readers/structured_data/__init__.py
llama_index/readers/structured_data/base.py
llama_index_readers_structured_data-0.4.1.dist-info/METADATA
llama_index_readers_structured_data-0.4.1.dist-info/WHEEL
llama_index_readers_structured_data-0.4.1.dist-info/licenses/LICENSE
llama_index_readers_structured_data-0.4.1.dist-info/RECORD
