Metadata-Version: 2.4
Name: llama-index-readers-structured-data
Version: 0.4.1
Summary: llama-index readers structured_data integration
Author-email: Haoran Chen <congling.chr@alibaba-inc.com>
License-Expression: MIT
License-File: LICENSE
Requires-Python: <4.0,>=3.9
Requires-Dist: llama-index-core<0.15,>=0.13.0
Requires-Dist: pandas
